rigol_ds1054z/__init__.py
rigol_ds1054z/utils.py
rigol_ds1054z/src/__init__.py
rigol_ds1054z/src/channel.py
rigol_ds1054z/src/display.py
rigol_ds1054z/src/ieee.py
rigol_ds1054z/src/oscope.py
rigol_ds1054z/src/timebase.py
rigol_ds1054z/src/trigger.py
rigol_ds1054z/src/waveform.py
rigol_ds1054z-1.0.1.dist-info/licenses/AUTHORS.md
rigol_ds1054z-1.0.1.dist-info/licenses/LICENSE
rigol_ds1054z-1.0.1.dist-info/METADATA
rigol_ds1054z-1.0.1.dist-info/WHEEL
rigol_ds1054z-1.0.1.dist-info/top_level.txt
rigol_ds1054z-1.0.1.dist-info/RECORD
