Metadata-Version: 2.4
Name: rigol-ds1054z
Version: 1.0.1
Summary: Python library for controlling Rigol DS1000Z series oscilloscopes via VISA (Virtual Instrument Software Architecture).
Maintainer-email: Ian Cleary <python@iancleary.me>
License-Expression: MIT
Requires-Python: >=3.13
License-File: LICENSE
License-File: AUTHORS.md
Requires-Dist: pyvisa>=1.15.0
Provides-Extra: tcpip
Requires-Dist: pyvisa-py>=0.8.1; extra == "tcpip"
Provides-Extra: ip
Requires-Dist: pyvisa-py>=0.8.1; extra == "ip"
Provides-Extra: usb
Requires-Dist: pyusb>=1.3.1; extra == "usb"
Dynamic: license-file
